my_utils/__init__.py
my_utils/dataset_utils.py
my_utils/datasets.py
my_utils/main.py
my_utils/tokenize.py
my_gentxt_utils-0.1.3.dist-info/METADATA
my_gentxt_utils-0.1.3.dist-info/WHEEL
my_gentxt_utils-0.1.3.dist-info/RECORD
